sentinella-0.5-nspkg.pth
sentinella-0.5.dist-info/METADATA
sentinella-0.5.dist-info/WHEEL
sentinella-0.5.dist-info/DESCRIPTION.rst
sentinella-0.5.dist-info/metadata.json
sentinella-0.5.dist-info/entry_points.txt
sentinella-0.5.dist-info/RECORD
sentinella-0.5.dist-info/namespace_packages.txt
sentinella-0.5.dist-info/top_level.txt
sentinella/agent/cli.py
sentinella/agent/__init__.py
sentinella/agent/agent2/agent.py
sentinella/agent/agent2/__init__.py
sentinella/metrics/__init__.py
sentinella/metrics/metrics2/metrics.py
sentinella/metrics/metrics2/__init__.py
sentinella/metrics/metrics/metrics.py
sentinella/metrics/metrics/__init__.py
sentinella/openstack_logs/__init__.py
sentinella/openstack_logs/openstack_logs.py
